awl/__init__.py
awl/absmodels.py
awl/admintools.py
awl/appmanage.py
awl/context_processors.py
awl/css_colours.py
awl/decorators.py
awl/logtools.py
awl/models.py
awl/utils.py
awl/waelsteng.py
awl/management/__init__.py
awl/management/commands/__init__.py
awl/management/commands/create_cmd.py
awl/management/commands/create_test_admin.py
awl/management/commands/print_setting.py
awl/management/commands/run_script.py
awl/management/commands/wipe_migrations.py
awl/management/commands/wtest.py
awl/migrations/0001_initial.py
awl/migrations/0002_alter_counter_id_alter_lock_id.py
awl/migrations/__init__.py
awl/rankedmodel/__init__.py
awl/rankedmodel/admintools.py
awl/rankedmodel/models.py
awl/rankedmodel/urls.py
awl/rankedmodel/views.py
awl/templatetags/__init__.py
awl/templatetags/awltags.py
django_awl-1.9.0.dist-info/licenses/LICENSE
django_awl-1.9.0.dist-info/METADATA
django_awl-1.9.0.dist-info/WHEEL
django_awl-1.9.0.dist-info/entry_points.txt
django_awl-1.9.0.dist-info/top_level.txt
django_awl-1.9.0.dist-info/RECORD
