Metadata-Version: 2.4
Name: django-awl
Version: 1.9.0
Summary: Collection of Django utilities
Author-email: Christopher Trudeau <ctrudeau+pypi@arsensa.com>
License: The MIT License (MIT)
Project-URL: repository, https://github.com/cltrudeau/django-awl
Project-URL: documentation, https://django-awl.readthedocs.io/en/latest/index.html
Classifier: Development Status :: 4 - Beta
Classifier: Environment :: Web Environment
Classifier: Intended Audience :: Developers
Classifier: License :: OSI Approved :: MIT License
Classifier: Operating System :: OS Independent
Classifier: Programming Language :: Python :: 3.8
Classifier: Programming Language :: Python :: 3.9
Classifier: Programming Language :: Python :: 3.10
Classifier: Programming Language :: Python :: 3.11
Classifier: Programming Language :: Python :: 3.12
Classifier: Programming Language :: Python :: 3.13
Classifier: Topic :: Software Development :: Libraries :: Application Frameworks
Classifier: Topic :: Software Development :: Libraries :: Python Modules
License-File: LICENSE
Requires-Dist: Django<6,>=4.2
Requires-Dist: logthing>=1.0.0
Requires-Dist: screwdriver>=0.15.0
Requires-Dist: waelstow>=0.12.0
Provides-Extra: build
Requires-Dist: build==1.2.2.post1; extra == "build"
Requires-Dist: twine==6.1.0; extra == "build"
Provides-Extra: dev
Requires-Dist: Django==5.1.5; extra == "dev"
Requires-Dist: context-temp==0.11.2; extra == "dev"
Requires-Dist: coverage==7.6.10; extra == "dev"
Requires-Dist: pudb==2024.1; extra == "dev"
Requires-Dist: pyflakes==3.2.0; extra == "dev"
Requires-Dist: Sphinx==8.1.3; extra == "dev"
Requires-Dist: sphinx-rtd-theme==3.0.2; extra == "dev"
Requires-Dist: nox==2024.10.9; extra == "dev"
Dynamic: license-file
